adacat/__init__.py
adacat/jax.py
adacat/torch.py
adacat-0.4.2.dist-info/LICENSE
adacat-0.4.2.dist-info/METADATA
adacat-0.4.2.dist-info/WHEEL
adacat-0.4.2.dist-info/top_level.txt
adacat-0.4.2.dist-info/RECORD
