Metadata-Version: 2.1
Name: adacat
Version: 0.4.2
Summary: Adaptive categorical distribution
Home-page: https://github.com/ColinQiyangLi/AdaCat-pip
Author: Qiyang Li
Author-email: colin.qiyang.li@gmail.com
Classifier: Programming Language :: Python
Classifier: Programming Language :: Python :: 3
Classifier: License :: OSI Approved :: GNU General Public License (GPL)
Classifier: Operating System :: OS Independent
Classifier: Development Status :: 1 - Planning
Classifier: Environment :: Console
Classifier: Intended Audience :: Science/Research
Classifier: Topic :: Scientific/Engineering :: GIS
License-File: LICENSE
